MANIFEST.in
README
example.xod
optimize.py
run_slow.sh
setup.py
slow.egg-info/PKG-INFO
slow.egg-info/SOURCES.txt
slow.egg-info/entry_points.txt
slow.egg-info/requires.txt
slow.egg-info/top_level.txt
src/slow/__init__.py
src/slow/codegen/helpers.py
src/slow/codegen/java_helpers.py
src/slow/model/__init__.py
src/slow/model/attribute_model.py
src/slow/model/code_model.py
src/slow/model/edsm_model.py
src/slow/model/file_model.py
src/slow/model/gui_model.py
src/slow/model/message_hierarchy_model.py
src/slow/model/model.py
src/slow/model/preference_model.py
src/slow/model/slosl_model.py
src/slow/model/sqldata_model.py
src/slow/model/xdr_model.py
src/slow/model/xpathmodel.py
src/slow/pyexec/__init__.py
src/slow/pyexec/db/helpers.py
src/slow/pyexec/db/slosl2sql.py
src/slow/pyexec/db/sqldb.py
src/slow/pyexec/networking/__init__.py
src/slow/pyexec/networking/message_builder.py
src/slow/pyexec/pydb/__init__.py
src/slow/pyexec/pydb/db.py
src/slow/pyexec/pydb/expression.py
src/slow/pyexec/pydb/node.py
src/slow/pyexec/pydb/views.py
src/slow/pyexec/pydb/viewspec.py
src/slow/pyexec/pyedsm/edsm.py
src/slow/pyexec/pyedsm/edsm_builder.py
src/slow/pyexec/pyedsm/helpers.py
src/slow/pyexec/pyedsm/states.py
src/slow/pyexec/pyedsm/twisted_edsm.py
src/slow/pyexec/utils/__init__.py
src/slow/pyexec/utils/misc.py
src/slow/pyexec/utils/observable.py
src/slow/qtgui/Makefile
src/slow/qtgui/__init__.py
src/slow/qtgui/aboutdialog.ui
src/slow/qtgui/attribute_editor.py
src/slow/qtgui/custom_widgets.py
src/slow/qtgui/edsm_editor.py
src/slow/qtgui/genaboutdialog.py
src/slow/qtgui/gengui.py
src/slow/qtgui/genprefdialog.py
src/slow/qtgui/genstatedialog.py
src/slow/qtgui/gentimerdialog.py
src/slow/qtgui/gentransitiondialog.py
src/slow/qtgui/gui.pro
src/slow/qtgui/gui.py
src/slow/qtgui/gui.ui
src/slow/qtgui/gui.ui.h
src/slow/qtgui/gui_interface.py
src/slow/qtgui/message_editor.py
src/slow/qtgui/popupmenu.py
src/slow/qtgui/prefdialog.ui
src/slow/qtgui/preference_dialog.py
src/slow/qtgui/qt_utils.py
src/slow/qtgui/slosl_editor.py
src/slow/qtgui/statedialog.ui
src/slow/qtgui/timerdialog.ui
src/slow/qtgui/transitiondialog.ui
