Metadata-Version: 1.0
Name: slow
Version: 0.3.3
Summary: SLOW - The SLOSL Overlay Workbench
Home-page: http://developer.berlios.de/projects/slow/
Author: Stefan Behnel
Author-email: scoder@users.berlios.de
License: UNKNOWN
Platform: UNKNOWN
Classifier: Development Status :: 3 - Alpha
Classifier: Intended Audience :: Developers
Classifier: Environment :: X11 Applications :: Qt
Classifier: Operating System :: OS Independent
Classifier: Programming Language :: Python
Classifier: License :: OSI Approved :: GNU General Public License (GPL)
Classifier: Intended Audience :: Science/Research
Classifier: Topic :: Communications
Classifier: Topic :: Internet
Classifier: Topic :: Scientific/Engineering :: Visualization
Classifier: Topic :: Software Development :: Code Generators
Classifier: Topic :: System :: Distributed Computing
Classifier: Topic :: System :: Networking
